[
    
  {
    "strName" : "Tick1HourExerciseStrengthTrainer",
    "strTitle" : "Силовая тренировка",
    "strDesc" : "Фокус на силовых тренировках в свободное время\n(усталость и затраты на гигиену)",
    "strActionGroup" : "Use",
    "strColor"      : "Dialogue",
    "aInverse"          : [
    ],
    "fDuration"         : 0.00,
    "strThemType"       : "Self",
    "nLogging"         : 0,
    "bHumanOnly"     : false,
    "CTTestUs"     : "TIsValidTick1HourExerciseStrengthTrainer",
    "LootCondsUs"       : null,
    "LootCTsUs"      : "CTTick1HourExerciseStrengthTrainerUs",
    "aSocialNew" : [
    ]
  },
  {
    "strName" : "Tick1HourExerciseTreadmill",
    "strTitle" : "Фитнес-тренировка",
    "strDesc" : "Фокус на кардио-тренировке в свободное время\n(усталость и затраты на гигиену)",
    "strActionGroup" : "Use",
    "strColor"      : "Dialogue",
    "aInverse"          : [
    ],
    "fDuration"         : 0.00,
    "strThemType"       : "Self",
    "nLogging"         : 0,
    "bHumanOnly"     : false,
    "CTTestUs"     : "TIsValidTick1HourExerciseTreadmill",
    "LootCondsUs"       : null,
    "LootCTsUs"      : "CTTick1HourExerciseTreadmillUs",
    "aSocialNew" : [
    ]
  },
  
  {
    "strName" : "Tick1HourSleepComfortably",
    "strTitle" : "Удобный сон (вне смены)",
    "strDesc" : "Фокус на комфортном сне в свободное время\n(менее эффективно вне смены)",
    "strActionGroup" : "Use",
    "strColor"      : "Dialogue",
    "aInverse"          : [
    ],
    "fDuration"         : 0.00,
    "strThemType"       : "Self",
    "nLogging"         : 0,
    "bHumanOnly"     : false,
    "CTTestUs"     : "TIsValidTick1HourSleepComfortablyOffSleepShift",
    "LootCondsUs"       : "CONDTick1HourSleepComfortably",
    "LootCTsUs"      : "CTTick1HourSleepComfortably",
    "aSocialNew" : [
    ]
  },
  {
    "strName" : "Tick1HourSleepComfortablyOnSleepShift",
    "strTitle" : "Комфортный сон",
    "strDesc" : "Фокус на комфортном сне в свободное время",
    "strActionGroup" : "Use",
    "strColor"      : "Dialogue",
    "aInverse"          : [
    ],
    "fDuration"         : 0.00,
    "strThemType"       : "Self",
    "nLogging"         : 0,
    "bHumanOnly"     : false,
    "CTTestUs"     : "TIsValidTick1HourSleepComfortablyOnSleepShift",
    "LootCondsUs"       : "CONDTick1HourSleepComfortably",
    "LootCTsUs"      : "CTTick1HourSleepComfortably",
    "aSocialNew" : [
    ]
  },
  {
    "strName" : "Tick1HourSleep",
    "strTitle" : "Сон (вне смены)",
    "strDesc" : "Фокус на попытках уснуть в свободное время\n(менее эффективно вне смены)",
    "strActionGroup" : "Use",
    "strColor"      : "Dialogue",
    "aInverse"          : [
    ],
    "fDuration"         : 0.00,
    "strThemType"       : "Self",
    "nLogging"         : 0,
    "bHumanOnly"     : false,
    "CTTestUs"     : "TIsValidTick1HourSleepOffSleepShift",
    "LootCondsUs"       : "CONDTick1HourSleep",
    "aSocialNew" : [
    ]
  },
  {
    "strName" : "Tick1HourSleepOnSleepShift",
    "strTitle" : "Сон",
    "strDesc" : "Фокус на попытках уснуть в свободное время",
    "strActionGroup" : "Use",
    "strColor"      : "Dialogue",
    "aInverse"          : [
    ],
    "fDuration"         : 0.00,
    "strThemType"       : "Self",
    "nLogging"         : 0,
    "bHumanOnly"     : false,
    "CTTestUs"     : "TIsValidTick1HourSleepOnSleepShift",
    "LootCondsUs"       : "CONDTick1HourSleep",
    "aSocialNew" : [
    ]
  },
  {
    "strName" : "Tick1HourSleepMedical",
    "strTitle" : "Медицинское восстановление (вне смены)",
    "strDesc" : "Фокус на попытках выздороветь в свободное время\n(менее эффективно вне смены)",
    "strActionGroup" : "Use",
    "strColor"      : "Dialogue",
    "aInverse"          : [
    ],
    "fDuration"         : 0.00,
    "strThemType"       : "Self",
    "nLogging"         : 0,
    "bHumanOnly"     : false,
    "CTTestUs"     : "TIsValidTick1HourSleepMedicalOffSleepShift",
    "LootCondsUs"       : "CONDTick1HourSleepMedical",
    "LootCTsUs"      : null,
    "aSocialNew" : [
    ]
  },
  {
    "strName" : "Tick1HourSleepMedicalOnSleepShift",
    "strTitle" : "Медицинское восстановление",
    "strDesc" : "Фокус на попытках выздороветь в свободное время",
    "strActionGroup" : "Use",
    "strColor"      : "Dialogue",
    "aInverse"          : [
    ],
    "fDuration"         : 0.00,
    "strThemType"       : "Self",
    "nLogging"         : 0,
    "bHumanOnly"     : false,
    "CTTestUs"     : "TIsValidTick1HourSleepMedicalOnSleepShift",
    "LootCondsUs"       : "CONDTick1HourSleepMedical",
    "LootCTsUs"      : null,
    "aSocialNew" : [
    ]
  },
  {
    "strName" : "Tick1HourIncapacitated",
    "strTitle" : "Недееспособный",
    "strDesc" : "Не может выполнять никакие действия",
    "strActionGroup" : "Use",
    "strColor"      : "Dialogue",
    "aInverse"          : [
    ],
    "fDuration"         : 0.00,
    "strThemType"       : "Self",
    "nLogging"         : 0,
    "bHumanOnly"     : false,
    "CTTestUs"     : "TIsValidTick1HourIncapacitated",
    "LootCondsUs"       : "CONDTick1HourIncapacitated",
    "LootCTsUs"      : null,
    "aSocialNew" : [
    ]
  },
  {
    "strName" : "Tick1HourDead",
    "strTitle" : "Мёртвый",
    "strDesc" : "Мёртвый",
    "strActionGroup" : "Use",
    "strColor"      : "Dialogue",
    "aInverse"          : [
    ],
    "fDuration"         : 0.00,
    "strThemType"       : "Self",
    "nLogging"         : 0,
    "bHumanOnly"     : false,
    "CTTestUs"     : "TIsValidTick1HourDead",
    "LootCondsUs"       : null,
    "LootCTsUs"      : null,
    "aSocialNew" : [
    ]
  },
  {
    "strName" : "Tick1HourShiftSleep",
    "strTitle" : "Отдых",
    "strDesc" : "Фокус на попытках отдохнуть во время смены сна",
    "strActionGroup" : "Use",
    "strColor"      : "Dialogue",
    "aInverse"          : [
    ],
    "fDuration"         : 0.00,
    "strThemType"       : "Self",
    "nLogging"         : 0,
    "bHumanOnly"     : false,
    "CTTestUs"     : "TIsShiftSleep",
    "LootCondsUs"       : "CONDTick1HourShiftSleep",
    "LootCTsUs"      : null,
    "aSocialNew" : [
    ]
  },
  {
    "strName" : "Tick1HourShiftFree",
    "strTitle" : "Свободное время",
    "strDesc" : "Фокус на расслаблении и наслаждении свободной сменой.",
    "strActionGroup" : "Use",
    "strColor"      : "Dialogue",
    "aInverse"          : [
    ],
    "fDuration"         : 0.00,
    "strThemType"       : "Self",
    "nLogging"         : 0,
    "bHumanOnly"     : false,
    "CTTestUs"     : "TIsShiftFree",
    "LootCondsUs"       : "CONDTick1HourFree",
    "LootCTsUs"      : null,
    "aSocialNew" : [
    ]
  },
  {
    "strName" : "Tick1HourShiftWork",
    "strTitle" : "Работа",
    "strDesc" : "Фокус на обязанностях и обслуживании корабля во время рабочей смены.",
    "strActionGroup" : "Use",
    "strColor"      : "Dialogue",
    "aInverse"          : [
    ],
    "fDuration"         : 0.00,
    "strThemType"       : "Self",
    "nLogging"         : 0,
    "bHumanOnly"     : false,
    "CTTestUs"     : "TIsShiftWork",
    "LootCondsUs"       : "CONDTick1HourWork",
    "LootCTsUs"      : null,
    "aSocialNew" : [
    ]
  },

  {
    "strName" : "Tick1HourStudyEngConstruction",
    "strTitle" : "Обучение строительной инженерии",
    "strDesc" : "Фокус на обучении строительной инженерии в свободное время",
    "strActionGroup" : "Use",
    "strColor"      : "Dialogue",
    "aInverse"          : [
    ],
    "fDuration"         : 0.00,
    "strThemType"       : "Self",
    "nLogging"         : 2,
    "bHumanOnly"     : false,
    "CTTestUs"     : "TIsValidTick1HourStudyEngConstruction",
    "LootCondsUs"       : null,
    "LootCTsUs"      : "CTTick1HourStudyEngConstructionUs",
    "aSocialNew" : [
    ]
  },
  {
    "strName" : "Tick1HourStudyEngCivil",
    "strTitle" : "Обучение гражданской инженерии",
    "strDesc" : "Фокус на обучении гражданской инженерии в свободное время",
    "strActionGroup" : "Use",
    "strColor"      : "Dialogue",
    "aInverse"          : [
    ],
    "fDuration"         : 0.00,
    "strThemType"       : "Self",
    "nLogging"         : 2,
    "bHumanOnly"     : false,
    "CTTestUs"     : "TIsValidTick1HourStudyEngCivil",
    "LootCondsUs"       : null,
    "LootCTsUs"      : "CTTick1HourStudyEngCivilUs",
    "aSocialNew" : [
    ]
  },
  {
    "strName" : "Tick1HourStudyEngCombat",
    "strTitle" : "Обучение боевой инженерии",
    "strDesc" : "Фокус на обучении боевой инженерии в свободное время",
    "strActionGroup" : "Use",
    "strColor"      : "Dialogue",
    "aInverse"          : [
    ],
    "fDuration"         : 0.00,
    "strThemType"       : "Self",
    "nLogging"         : 2,
    "bHumanOnly"     : false,
    "CTTestUs"     : "TIsValidTick1HourStudyEngCombat",
    "LootCondsUs"       : null,
    "LootCTsUs"      : "CTTick1HourStudyEngCombatUs",
    "aSocialNew" : [
    ]
  },
  {
    "strName" : "Tick1HourStudyEngElectronic",
    "strTitle" : "Обучение электротехнике",
    "strDesc" : "Фокус на обучении электротехнике в свободное время",
    "strActionGroup" : "Use",
    "strColor"      : "Dialogue",
    "aInverse"          : [
    ],
    "fDuration"         : 0.00,
    "strThemType"       : "Self",
    "nLogging"         : 2,
    "bHumanOnly"     : false,
    "CTTestUs"     : "TIsValidTick1HourStudyEngElectronic",
    "LootCondsUs"       : null,
    "LootCTsUs"      : "CTTick1HourStudyEngElectronicUs",
    "aSocialNew" : [
    ]
  },
  {
    "strName" : "Tick1HourStudyEngMechanical",
    "strTitle" : "Обучение механической инженерии",
    "strDesc" : "Фокус на обучении механической инженерии в свободное время",
    "strActionGroup" : "Use",
    "strColor"      : "Dialogue",
    "aInverse"          : [
    ],
    "fDuration"         : 0.00,
    "strThemType"       : "Self",
    "nLogging"         : 2,
    "bHumanOnly"     : false,
    "CTTestUs"     : "TIsValidTick1HourStudyEngMechanical",
    "LootCondsUs"       : null,
    "LootCTsUs"      : "CTTick1HourStudyEngMechanicalUs",
    "aSocialNew" : [
    ]
  },
  {
    "strName" : "Tick1HourStudyEngRobotics",
    "strTitle" : "Обучение робототехнике",
    "strDesc" : "Фокус на обучении робототехнике в свободное время",
    "strActionGroup" : "Use",
    "strColor"      : "Dialogue",
    "aInverse"          : [
    ],
    "fDuration"         : 0.00,
    "strThemType"       : "Self",
    "nLogging"         : 2,
    "bHumanOnly"     : false,
    "CTTestUs"     : "TIsValidTick1HourStudyEngRobotics",
    "LootCondsUs"       : null,
    "LootCTsUs"      : "CTTick1HourStudyEngRoboticsUs",
    "aSocialNew" : [
    ]
  },
  {
    "strName" : "Tick1HourStudyEngSoftware",
    "strTitle" : "Обучение программной инженерии",
    "strDesc" : "Фокус на обучении программной инженерии в свободное время",
    "strActionGroup" : "Use",
    "strColor"      : "Dialogue",
    "aInverse"          : [
    ],
    "fDuration"         : 0.00,
    "strThemType"       : "Self",
    "nLogging"         : 2,
    "bHumanOnly"     : false,
    "CTTestUs"     : "TIsValidTick1HourStudyEngSoftware",
    "LootCondsUs"       : null,
    "LootCTsUs"      : "CTTick1HourStudyEngSoftwareUs",
    "aSocialNew" : [
    ]
  },
  {
    "strName" : "Tick1HourStudyEngSpaceship",
    "strTitle" : "Обучение корабельной инженерии",
    "strDesc" : "Фокус на обучении корабельной инженерии в свободное время",
    "strActionGroup" : "Use",
    "strColor"      : "Dialogue",
    "aInverse"          : [
    ],
    "fDuration"         : 0.00,
    "strThemType"       : "Self",
    "nLogging"         : 2,
    "bHumanOnly"     : false,
    "CTTestUs"     : "TIsValidTick1HourStudyEngSpaceship",
    "LootCondsUs"       : null,
    "LootCTsUs"      : "CTTick1HourStudyEngSpaceshipUs",
    "aSocialNew" : [
    ]
  },
  {
    "strName" : "Tick1HourStudyHacking",
    "strTitle" : "Обучение хакерству",
    "strDesc" : "Фокус на обучении хакерству в свободное время",
    "strActionGroup" : "Use",
    "strColor"      : "Dialogue",
    "aInverse"          : [
    ],
    "fDuration"         : 0.00,
    "strThemType"       : "Self",
    "nLogging"         : 2,
    "bHumanOnly"     : false,
    "CTTestUs"     : "TIsValidTick1HourStudyHacking",
    "LootCondsUs"       : null,
    "LootCTsUs"      : "CTTick1HourStudyHackingUs",
    "aSocialNew" : [
    ]
  },

  {
    "strName" : "FFWDEventAmbitious",
    "strTitle" : "Делимся мечтами (Амбициозный)",
    "strDesc" : "[us] рассказывает о своих мечтах и будущих успехах [them].",
    "strActionGroup" : "Use",
    "strColor"      : "Dialogue",
    "aInverse"          : [
    ],
    "fDuration"         : 0.00,
    "strThemType"       : "Other",
    "nLogging"         : 1,
    "bHumanOnly"     : false,
    "bSocial" : true,
    "CTTestUs"     : "TIsAmbitiousAwake",
    "CTTestThem" : "TIsValidSocialTarget",
    "LootCondsUs"       : "CONDFFWDEventAmbitiousUs",
    "LootCondsThem"       : "CONDFFWDEventAmbitiousThem",
    "ShipTestUs" : "PlayerCurrentShip",
    "ShipTestThem" : "PlayerCurrentShip"
  },
  {
    "strName" : "FFWDEventArrogant",
    "strTitle" : "Хвастается (Высокомерный)",
    "strDesc" : "[us] хвастается своими достижениями, забирая на себя заслуги [them].",
    "strActionGroup" : "Use",
    "strColor"      : "Dialogue",
    "aInverse"          : [
    ],
    "fDuration"         : 0.00,
    "strThemType"       : "Other",
    "nLogging"         : 1,
    "bHumanOnly"     : false,
    "bSocial" : true,
    "CTTestUs"     : "TIsArrogantAwake",
    "CTTestThem" : "TIsValidSocialTarget",
    "LootCondsUs"       : "CONDFFWDEventArrogantUs",
    "LootCondsThem"       : "CONDFFWDEventArrogantThem",
    "ShipTestUs" : "PlayerCurrentShip",
    "ShipTestThem" : "PlayerCurrentShip"
  },
  {
    "strName" : "FFWDEventBrave",
    "strTitle" : "Вдохновляем (Смелый)",
    "strDesc" : "[us] вдохновляет [them], преодолевая страхи и трудности.",
    "strActionGroup" : "Use",
    "strColor"      : "Dialogue",
    "aInverse"          : [
    ],
    "fDuration"         : 0.00,
    "strThemType"       : "Other",
    "nLogging"         : 1,
    "bHumanOnly"     : false,
    "bSocial" : true,
    "CTTestUs"     : "TIsBraveAwake",
    "CTTestThem" : "TIsValidSocialTarget",
    "LootCondsUs"       : "CONDFFWDEventBraveUs",
    "LootCondsThem"       : "CONDFFWDEventBraveThem",
    "ShipTestUs" : "PlayerCurrentShip",
    "ShipTestThem" : "PlayerCurrentShip",
    "LootCTsUs"      : null,
    "aSocialNew" : [
    ]
  },
  {
    "strName" : "FFWDEventCharismatic",
    "strTitle" : "Вдохновляем (Харизматичный)",
    "strDesc" : "[us] вдохновляет [them] новым чувством цели.",
    "strActionGroup" : "Use",
    "strColor"      : "Dialogue",
    "aInverse"          : [
    ],
    "fDuration"         : 0.00,
    "strThemType"       : "Other",
    "nLogging"         : 1,
    "bHumanOnly"     : false,
    "bSocial" : true,
    "CTTestUs"     : "TIsCharismaticAwake",
    "CTTestThem" : "TIsValidSocialTarget",
    "LootCondsUs"       : "CONDFFWDEventCharismaticUs",
    "LootCondsThem"       : "CONDFFWDEventCharismaticThem",
    "ShipTestUs" : "PlayerCurrentShip",
    "ShipTestThem" : "PlayerCurrentShip"
  },
  {
    "strName" : "FFWDEventComedian",
    "strTitle" : "Развлекаем (Комедиант)",
    "strDesc" : "[us] развлекает [them] юмором.",
    "strActionGroup" : "Use",
    "strColor"      : "Dialogue",
    "aInverse"          : [
    ],
    "fDuration"         : 0.00,
    "strThemType"       : "Other",
    "nLogging"         : 1,
    "bHumanOnly"     : false,
    "bSocial" : true,
    "CTTestUs"     : "TIsComedianAwake",
    "CTTestThem" : "TIsValidSocialTarget",
    "LootCondsUs"       : "CONDFFWDEventComedianUs",
    "LootCondsThem"       : "CONDFFWDEventComedianThem",
    "ShipTestUs" : "PlayerCurrentShip",
    "ShipTestThem" : "PlayerCurrentShip"
  },
  {
    "strName" : "FFWDEventCraven",
    "strTitle" : "Делимся страхами (Трусливый)",
    "strDesc" : "[us] беспокоится о своих страхах перед [them].",
    "strActionGroup" : "Use",
    "strColor"      : "Dialogue",
    "aInverse"          : [
    ],
    "fDuration"         : 0.00,
    "strThemType"       : "Other",
    "nLogging"         : 1,
    "bHumanOnly"     : false,
    "bSocial" : true,
    "CTTestUs"     : "TIsCravenAwake",
    "CTTestThem" : "TIsValidSocialTarget",
    "LootCondsUs"       : "CONDFFWDEventCravenUs",
    "LootCondsThem"       : "CONDFFWDEventCravenThem",
    "ShipTestUs" : "PlayerCurrentShip",
    "ShipTestThem" : "PlayerCurrentShip"
  },
  {
    "strName" : "FFWDEventDiligent",
    "strTitle" : "Получает комплимент (Усердный)",
    "strDesc" : "[us] получает комплимент от [them] за свои усердные усилия.",
    "strActionGroup" : "Use",
    "strColor"      : "Dialogue",
    "aInverse"          : [
    ],
    "fDuration"         : 0.00,
    "strThemType"       : "Other",
    "nLogging"         : 1,
    "bHumanOnly"     : false,
    "bSocial" : true,
    "CTTestUs"     : "TIsDiligentAwake",
    "CTTestThem" : "TIsValidSocialTarget",
    "LootCondsUs"       : "CONDFFWDEventDiligentUs",
    "LootCondsThem"       : "CONDFFWDEventDiligentThem",
    "ShipTestUs" : "PlayerCurrentShip",
    "ShipTestThem" : "PlayerCurrentShip"
  },
  {
    "strName" : "FFWDEventFinicky",
    "strTitle" : "Жалуется (Привередливый)",
    "strDesc" : "[us] излишне жалуется [them] на ряд мелких деталей.",
    "strActionGroup" : "Use",
    "strColor"      : "Dialogue",
    "aInverse"          : [
    ],
    "fDuration"         : 0.00,
    "strThemType"       : "Other",
    "nLogging"         : 1,
    "bHumanOnly"     : false,
    "bSocial" : true,
    "CTTestUs"     : "TIsFinickyAwake",
    "CTTestThem" : "TIsValidSocialTarget",
    "LootCondsUs"       : "CONDFFWDEventFinickyUs",
    "LootCondsThem"       : "CONDFFWDEventFinickyThem",
    "ShipTestUs" : "PlayerCurrentShip",
    "ShipTestThem" : "PlayerCurrentShip"
  },
  {
    "strName" : "FFWDEventFollower",
    "strTitle" : "Ищет помощь (Последователь)",
    "strDesc" : "[us] просит совета у [them] по основным жизненным решениям.",
    "strActionGroup" : "Use",
    "strColor"      : "Dialogue",
    "aInverse"          : [
    ],
    "fDuration"         : 0.00,
    "strThemType"       : "Other",
    "nLogging"         : 1,
    "bHumanOnly"     : false,
    "bSocial" : true,
    "CTTestUs"     : "TIsFollowerAwake",
    "CTTestThem" : "TIsValidSocialTarget",
    "LootCondsUs"       : "CONDFFWDEventFollowerUs",
    "LootCondsThem"       : "CONDFFWDEventFollowerThem",
    "ShipTestUs" : "PlayerCurrentShip",
    "ShipTestThem" : "PlayerCurrentShip"
  },
  {
    "strName" : "FFWDEventForgiving",
    "strTitle" : "Прощает (Прощающий)",
    "strDesc" : "[us] прощает [them] за ранее совершённое правонарушение.",
    "strActionGroup" : "Use",
    "strColor"      : "Dialogue",
    "aInverse"          : [
    ],
    "fDuration"         : 0.00,
    "strThemType"       : "Other",
    "nLogging"         : 1,
    "bHumanOnly"     : false,
    "bSocial" : true,
    "CTTestUs"     : "TIsForgivingAwake",
    "CTTestThem" : "TIsValidSocialTarget",
    "LootCondsUs"       : "CONDFFWDEventForgivingUs",
    "LootCondsThem"       : "CONDFFWDEventForgivingThem",
    "ShipTestUs" : "PlayerCurrentShip",
    "ShipTestThem" : "PlayerCurrentShip"
  },
  {
    "strName" : "FFWDEventGenius",
    "strTitle" : "Развивает теории (Гений)",
    "strDesc" : "[us] развивает блестящие теории для [them].",
    "strActionGroup" : "Use",
    "strColor"      : "Dialogue",
    "aInverse"          : [
    ],
    "fDuration"         : 0.00,
    "strThemType"       : "Other",
    "nLogging"         : 1,
    "bHumanOnly"     : false,
    "bSocial" : true,
    "CTTestUs"     : "TIsGeniusAwake",
    "CTTestThem" : "TIsValidSocialTarget",
    "LootCondsUs"       : "CONDFFWDEventGeniusUs",
    "LootCondsThem"       : "CONDFFWDEventGeniusThem",
    "ShipTestUs" : "PlayerCurrentShip",
    "ShipTestThem" : "PlayerCurrentShip"
  },
  {
    "strName" : "FFWDEventGlutton",
    "strTitle" : "Делимся желаниями о вкусной еде (Обжора)",
    "strDesc" : "[us] не может перестать рассказывать [them] о желаниях к вкусной, недоступной еде.",
    "strActionGroup" : "Use",
    "strColor"      : "Dialogue",
    "aInverse"          : [
    ],
    "fDuration"         : 0.00,
    "strThemType"       : "Other",
    "nLogging"         : 1,
    "bHumanOnly"     : false,
    "bSocial" : true,
    "CTTestUs"     : "TIsGluttonAwake",
    "CTTestThem" : "TIsValidSocialTarget",
    "LootCondsUs"       : "CONDFFWDEventGluttonUs",
    "LootCondsThem"       : "CONDFFWDEventGluttonThem",
    "ShipTestUs" : "PlayerCurrentShip",
    "ShipTestThem" : "PlayerCurrentShip"
  },
  {
    "strName" : "FFWDEventGregarious",
    "strTitle" : "Наслаждается компанией (Общительный)",
    "strDesc" : "[us] тепло наслаждается обществом [them].",
    "strActionGroup" : "Use",
    "strColor"      : "Dialogue",
    "aInverse"          : [
    ],
    "fDuration"         : 0.00,
    "strThemType"       : "Other",
    "nLogging"         : 1,
    "bHumanOnly"     : false,
    "bSocial" : true,
    "CTTestUs"     : "TIsGregariousAwake",
    "CTTestThem" : "TIsValidSocialTarget",
    "LootCondsUs"       : "CONDFFWDEventGregariousUs",
    "LootCondsThem"       : "CONDFFWDEventGregariousThem",
    "ShipTestUs" : "PlayerCurrentShip",
    "ShipTestThem" : "PlayerCurrentShip"
  },
  {
    "strName" : "FFWDEventHonest",
    "strTitle" : "Говорит горькую правду (Честный)",
    "strDesc" : "[us] говорит [them] горькую, неудобную правду.",
    "strActionGroup" : "Use",
    "strColor"      : "Dialogue",
    "aInverse"          : [
    ],
    "fDuration"         : 0.00,
    "strThemType"       : "Other",
    "nLogging"         : 1,
    "bHumanOnly"     : false,
    "bSocial" : true,
    "CTTestUs"     : "TIsHonestAwake",
    "CTTestThem" : "TIsValidSocialTarget",
    "LootCondsUs"       : "CONDFFWDEventHonestUs",
    "LootCondsThem"       : "CONDFFWDEventHonestThem",
    "ShipTestUs" : "PlayerCurrentShip",
    "ShipTestThem" : "PlayerCurrentShip"
  },
  {
    "strName" : "FFWDEventHumble",
    "strTitle" : "Делится заслугами (Скромный)",
    "strDesc" : "[us] позволяет [them] насладиться признанием за совместные усилия.",
    "strActionGroup" : "Use",
    "strColor"      : "Dialogue",
    "aInverse"          : [
    ],
    "fDuration"         : 0.00,
    "strThemType"       : "Other",
    "nLogging"         : 1,
    "bHumanOnly"     : false,
    "bSocial" : true,
    "CTTestUs"     : "TIsHumbleAwake",
    "CTTestThem" : "TIsValidSocialTarget",
    "LootCondsUs"       : "CONDFFWDEventHumbleUs",
    "LootCondsThem"       : "CONDFFWDEventHumbleThem",
    "ShipTestUs" : "PlayerCurrentShip",
    "ShipTestThem" : "PlayerCurrentShip"
  },
  {
    "strName" : "FFWDEventHumorless",
    "strTitle" : "Убивает веселье (Безюморный)",
    "strDesc" : "[us] подавляет легкость и игривость, которые [them] пытается внести в ситуацию.",
    "strActionGroup" : "Use",
    "strColor"      : "Dialogue",
    "aInverse"          : [
    ],
    "fDuration"         : 0.00,
    "strThemType"       : "Other",
    "nLogging"         : 1,
    "bHumanOnly"     : false,
    "bSocial" : true,
    "CTTestUs"     : "TIsHumorlessAwake",
    "CTTestThem" : "TIsValidSocialTarget",
    "LootCondsUs"       : "CONDFFWDEventHumorlessUs",
    "LootCondsThem"       : "CONDFFWDEventHumorlessThem",
    "ShipTestUs" : "PlayerCurrentShip",
    "ShipTestThem" : "PlayerCurrentShip"
  },
  {
    "strName" : "FFWDEventImpatient",
    "strTitle" : "Нетерпеливый (Нетерпеливый)",
    "strDesc" : "[us] жалуется [them] на потраченное время и нетерпеливо ждет.",
    "strActionGroup" : "Use",
    "strColor"      : "Dialogue",
    "aInverse"          : [
    ],
    "fDuration"         : 0.00,
    "strThemType"       : "Other",
    "nLogging"         : 1,
    "bHumanOnly"     : false,
    "bSocial" : true,
    "CTTestUs"     : "TIsImpatientAwake",
    "CTTestThem" : "TIsValidSocialTarget",
    "LootCondsUs"       : "CONDFFWDEventImpatientUs",
    "LootCondsThem"       : "CONDFFWDEventImpatientThem",
    "ShipTestUs" : "PlayerCurrentShip",
    "ShipTestThem" : "PlayerCurrentShip"
  },
  {
    "strName" : "FFWDEventKind",
    "strTitle" : "Поддерживает (Добрый)",
    "strDesc" : "[us] тепло поддерживает положительные аспекты [them].",
    "strActionGroup" : "Use",
    "strColor"      : "Dialogue",
    "aInverse"          : [
    ],
    "fDuration"         : 0.00,
    "strThemType"       : "Other",
    "nLogging"         : 1,
    "bHumanOnly"     : false,
    "bSocial" : true,
    "CTTestUs"     : "TIsKindAwake",
    "CTTestThem" : "TIsValidSocialTarget",
    "LootCondsUs"       : "CONDFFWDEventKindUs",
    "LootCondsThem"       : "CONDFFWDEventKindThem",
    "ShipTestUs" : "PlayerCurrentShip",
    "ShipTestThem" : "PlayerCurrentShip"
  },
  {
    "strName" : "FFWDEventLeader",
    "strTitle" : "Координирует (Лидер)",
    "strDesc" : "[us] мотивирует эффективные совместные усилия с [them].",
    "strActionGroup" : "Use",
    "strColor"      : "Dialogue",
    "aInverse"          : [
    ],
    "fDuration"         : 0.00,
    "strThemType"       : "Other",
    "nLogging"         : 1,
    "bHumanOnly"     : false,
    "bSocial" : true,
    "CTTestUs"     : "TIsLeaderAwake",
    "CTTestThem"     : "TIsPlayerCrew",
    "LootCondsUs"       : "CONDFFWDEventLeaderUs",
    "LootCondsThem"       : "CONDFFWDEventLeaderThem",
    "ShipTestUs" : "PlayerCurrentShip",
    "ShipTestThem" : "PlayerCurrentShip"
  },
  {
    "strName" : "FFWDEventLeader02",
    "strTitle" : "Воодушевляет (Лидер)",
    "strDesc" : "[us] поднимает настроение как [them], так и [3rd] с помощью воодушевляющей речью.",
    "strActionGroup" : "Use",
    "strColor"      : "Dialogue",
    "aInverse"          : [
    ],
    "fDuration"         : 0.00,
    "strThemType"       : "Other",
    "nLogging"         : 1,
    "bHumanOnly"     : false,
    "bSocial" : true,
    "CTTestUs"     : "TIsLeaderAwake",
    "CTTestThem" : "TIsPlayerCrew",
    "CTTest3rd" : "TIsPlayerCrew",
    "LootCondsUs"       : "CONDFFWDEventLeaderUs",
    "LootCondsThem"       : "CONDFFWDEventLeaderThem",
    "LootConds3rd"       : "CONDFFWDEventLeaderThem",
    "ShipTestUs" : "PlayerCurrentShip",
    "ShipTestThem" : "PlayerCurrentShip",
    "ShipTest3rd" : "PlayerCurrentShip"
  },
  {
    "strName" : "FFWDEventLiar",
    "strTitle" : "Обман (Лжец)",
    "strDesc" : "[us] добивается своего, манипулируя [them] с помощью обмана.",
    "strActionGroup" : "Use",
    "strColor"      : "Dialogue",
    "aInverse"          : [
    ],
    "fDuration"         : 0.00,
    "strThemType"       : "Other",
    "nLogging"         : 1,
    "bHumanOnly"     : false,
    "bSocial" : true,
    "CTTestUs"     : "TIsLiarAwake",
    "CTTestThem" : "TIsValidSocialTarget",
    "LootCondsUs"       : "CONDFFWDEventLiarUs",
    "LootCondsThem"       : "CONDFFWDEventLiarThem",
    "ShipTestUs" : "PlayerCurrentShip",
    "ShipTestThem" : "PlayerCurrentShip"
  },
  {
    "strName" : "FFWDEventLoyal",
    "strTitle" : "Поддерживает (Верный)",
    "strDesc" : "[us] поддерживает [them] в трудное время.",
    "strActionGroup" : "Use",
    "strColor"      : "Dialogue",
    "aInverse"          : [
    ],
    "fDuration"         : 0.00,
    "strThemType"       : "Other",
    "nLogging"         : 1,
    "bSocial" : true,
    "bHumanOnly"     : false,
    "CTTestUs"     : "TIsLoyalAwake",
    "CTTestThem" : "TIsValidSocialTarget",
    "LootCondsUs"       : "CONDFFWDEventLoyalUs",
    "LootCondsThem"       : "CONDFFWDEventLoyalThem",
    "ShipTestUs" : "PlayerCurrentShip",
    "ShipTestThem" : "PlayerCurrentShip"
  },
  {
    "strName" : "FFWDEventLustful",
    "strTitle" : "Непристойные шутки (Похотливый)",
    "strDesc" : "[us] шутит непристойно с [them].",
    "strActionGroup" : "Use",
    "strColor"      : "Dialogue",
    "aInverse"          : [
    ],
    "fDuration"         : 0.00,
    "strThemType"       : "Other",
    "nLogging"         : 1,
    "bHumanOnly"     : false,
    "bSocial" : true,
    "CTTestUs"     : "TIsLustfulAwake",
    "CTTestThem" : "TIsValidSocialTarget",
    "LootCondsUs"       : "CONDFFWDEventLustfulUs",
    "LootCondsThem"       : "CONDFFWDEventLustfulThem",
    "ShipTestUs" : "PlayerCurrentShip",
    "ShipTestThem" : "PlayerCurrentShip"
  },

  {
    "strName" : "FFWDEventMoodHygienePoor",
    "strTitle" : "Критика гигиены",
    "strDesc" : "[us] критикует [them] за неприятные гигиенические привычки.",
    "strActionGroup" : "Use",
    "strColor"      : "Dialogue",
    "aInverse"          : [
    ],
    "fDuration"         : 0.00,
    "strThemType"       : "Other",
    "nLogging"         : 1,
    "bHumanOnly"     : false,
    "bSocial" : true,
    "CTTestUs"     : "TCanCriticizePoorHygieneAwake",
    "CTTestThem" : "THasPoorHygiene",
    "LootCondsUs"       : "CONDFFWDEventMoodHygienePoorUs",
    "LootCondsThem"       : "CONDFFWDEventMoodHygienePoorThem",
    "ShipTestUs" : "PlayerCurrentShip",
    "ShipTestThem" : "PlayerCurrentShip"
  },
  {
    "strName" : "FFWDEventMoodAchievement",
    "strTitle" : "Жалуется на бесполезность",
    "strDesc" : "[us] жалуется [them] на то, что чувствует себя бесполезным.",
    "strActionGroup" : "Use",
    "strColor"      : "Dialogue",
    "aInverse"          : [
    ],
    "fDuration"         : 0.00,
    "strThemType"       : "Other",
    "nLogging"         : 1,
    "bHumanOnly"     : false,
    "bSocial" : true,
    "CTTestUs"     : "THasAchievement05Awake",
    "CTTestThem" : "TIsValidSocialTarget",
    "LootCondsUs"       : "CONDFFWDEventMoodAchievement",
    "LootCondsThem"       : "CONDFFWDEventMoodAchievement",
    "ShipTestUs" : "PlayerCurrentShip",
    "ShipTestThem" : "PlayerCurrentShip",
    "LootCTsUs"      : null
  },
  {
    "strName" : "FFWDEventMoodAltruismThem",
    "strTitle" : "Жалуется на эгоизм",
    "strDesc" : "[us] жалуется на [them], что тот слишком эгоистичен.",
    "strActionGroup" : "Use",
    "strColor"      : "Dialogue",
    "aInverse"          : [
    ],
    "fDuration"         : 0.00,
    "strThemType"       : "Other",
    "nLogging"         : 1,
    "bHumanOnly"     : false,
    "bSocial" : true,
    "CTTestUs" : "TIsValidSocialTarget",
    "CTTestThem"     : "THasAltruism05",
    "LootCondsUs"       : "CONDFFWDEventMoodAltruism",
    "LootCondsThem"       : "CONDFFWDEventMoodAltruism",
    "ShipTestUs" : "PlayerCurrentShip",
    "ShipTestThem" : "PlayerCurrentShip",
    "LootCTsUs"      : null
  },
  {
    "strName" : "FFWDEventMoodAltruism",
    "strTitle" : "Жалуется на то, что мы заслуживаем",
    "strDesc" : "[us] жалуется [them] о том, что им никогда не достаётся того, что они заслуживают.",
    "strActionGroup" : "Use",
    "strColor"      : "Dialogue",
    "aInverse"          : [
    ],
    "fDuration"         : 0.00,
    "strThemType"       : "Other",
    "nLogging"         : 1,
    "bHumanOnly"     : false,
    "bSocial" : true,
    "CTTestUs"     : "THasAltruism05Awake",
    "CTTestThem" : "TIsValidSocialTarget",
    "LootCondsUs"       : "CONDFFWDEventMoodAltruism",
    "LootCondsThem"       : "CONDFFWDEventMoodAltruism",
    "ShipTestUs" : "PlayerCurrentShip",
    "ShipTestThem" : "PlayerCurrentShip",
    "LootCTsUs"      : null
  },
  {
    "strName" : "FFWDEventMoodAutonomy",
    "strTitle" : "Жалуется на микроменеджмент",
    "strDesc" : "[us] жалуется [them] на то, что их постоянно микроменеджат и хотят отдохнуть.",
    "strActionGroup" : "Use",
    "strColor"      : "Dialogue",
    "aInverse"          : [
    ],
    "fDuration"         : 0.00,
    "strThemType"       : "Other",
    "nLogging"         : 1,
    "bHumanOnly"     : false,
    "bSocial" : true,
    "CTTestUs"     : "THasAutonomy05Awake",
    "CTTestThem" : "TIsValidSocialTarget",
    "LootCondsUs"       : "CONDFFWDEventMoodAutonomy",
    "LootCondsThem"       : "CONDFFWDEventMoodAutonomy",
    "ShipTestUs" : "PlayerCurrentShip",
    "ShipTestThem" : "PlayerCurrentShip",
    "LootCTsUs"      : null
  },
  {
    "strName" : "FFWDEventMoodContact",
    "strTitle" : "Жалуется на одиночество",
    "strDesc" : "[us] жалуется [them] о том, что им кажется, что их никто не слушает.",
    "strActionGroup" : "Use",
    "strColor"      : "Dialogue",
    "aInverse"          : [
    ],
    "fDuration"         : 0.00,
    "strThemType"       : "Other",
    "nLogging"         : 1,
    "bHumanOnly"     : false,
    "bSocial" : true,
    "CTTestUs"     : "THasContact05Awake",
    "CTTestThem" : "TIsValidSocialTarget",
    "LootCondsUs"       : "CONDFFWDEventMoodContact",
    "LootCondsThem"       : "CONDFFWDEventMoodContact",
    "ShipTestUs" : "PlayerCurrentShip",
    "ShipTestThem" : "PlayerCurrentShip",
    "LootCTsUs"      : null
  },
  {
    "strName" : "FFWDEventMoodEsteem",
    "strTitle" : "Жалуется на уважение",
    "strDesc" : "[us] жалуется [them] о том, что им кажется, что их никто не уважает.",
    "strActionGroup" : "Use",
    "strColor"      : "Dialogue",
    "aInverse"          : [
    ],
    "fDuration"         : 0.00,
    "strThemType"       : "Other",
    "nLogging"         : 1,
    "bHumanOnly"     : false,
    "bSocial" : true,
    "CTTestUs"     : "THasEsteem05Awake",
    "CTTestThem" : "TIsValidSocialTarget",
    "LootCondsUs"       : "CONDFFWDEventMoodEsteem",
    "LootCondsThem"       : "CONDFFWDEventMoodEsteem",
    "ShipTestUs" : "PlayerCurrentShip",
    "ShipTestThem" : "PlayerCurrentShip",
    "LootCTsUs"      : null
  },
  {
    "strName" : "FFWDEventMoodMeaning",
    "strTitle" : "Жалуется на бессмысленность",
    "strDesc" : "[us] жалуется [them] о том, что им кажется, что жизнь лишена смысла и красоты.",
    "strActionGroup" : "Use",
    "strColor"      : "Dialogue",
    "aInverse"          : [
    ],
    "fDuration"         : 0.00,
    "strThemType"       : "Other",
    "nLogging"         : 1,
    "bHumanOnly"     : false,
    "bSocial" : true,
    "CTTestUs"     : "THasMeaning05Awake",
    "CTTestThem" : "TIsValidSocialTarget",
    "LootCondsUs"       : "CONDFFWDEventMoodMeaningUs",
    "LootCondsThem"       : "CONDFFWDEventMoodMeaningThem",
    "ShipTestUs" : "PlayerCurrentShip",
    "ShipTestThem" : "PlayerCurrentShip",
    "LootCTsUs"      : null
  },
  {
    "strName" : "FFWDEventMoodSelfRespect",
    "strTitle" : "Жалуется на самоуважение",
    "strDesc" : "[us] выражает свои комплексы и самоубийство [them].",
    "strActionGroup" : "Use",
    "strColor"      : "Dialogue",
    "aInverse"          : [
    ],
    "fDuration"         : 0.00,
    "strThemType"       : "Other",
    "nLogging"         : 1,
    "bHumanOnly"     : false,
    "bSocial" : true,
    "CTTestUs"     : "TIsDcSelfRespect05Awake",
    "CTTestThem" : "TIsValidSocialTarget",
    "LootCondsUs"       : "CONDFFWDEventMoodSelfRespect",
    "LootCondsThem"       : "CONDFFWDEventMoodSelfRespect",
    "ShipTestUs" : "PlayerCurrentShip",
    "ShipTestThem" : "PlayerCurrentShip",
    "LootCTsUs"      : null
  },
  {
    "strName" : "FFWDEventMoodSecurity",
    "strTitle" : "Жалуется на тревогу",
    "strDesc" : "[us] выливается [them] о своих тревогах и чувстве ужаса.",
    "strActionGroup" : "Use",
    "strColor"      : "Dialogue",
    "aInverse"          : [
    ],
    "fDuration"         : 0.00,
    "strThemType"       : "Other",
    "nLogging"         : 1,
    "bHumanOnly"     : false,
    "bSocial" : true,
    "CTTestUs"     : "TIsDcSecurity05NotSleeping",
    "CTTestThem" : "TIsValidSocialTarget",
    "LootCondsUs"       : "CONDFFWDEventMoodSecurity",
    "LootCondsThem"       : "CONDFFWDEventMoodSecurity",
    "ShipTestUs" : "PlayerCurrentShip",
    "ShipTestThem" : "PlayerCurrentShip",
    "LootCTsUs"      : null
  },
  {
    "strName" : "FFWDEventMoodPrivacy",
    "strTitle" : "Пожаловаться на отсутствие личного пространства",
    "strDesc" : "[us] жалуется [them] на необходимость в пространстве и отсутствие личной жизни.",
    "strActionGroup" : "Use",
    "strColor"      : "Dialogue",
    "aInverse"          : [
    ],
    "fDuration"         : 0.00,
    "strThemType"       : "Other",
    "nLogging"         : 1,
    "bHumanOnly"     : false,
    "bSocial" : true,
    "CTTestUs"     : "TDiscomfortsPrivacyAwake",
    "CTTestThem" : "TIsValidSocialTarget",
    "LootCondsUs"       : "CONDFFWDEventMoodPrivacy",
    "LootCondsThem"       : "CONDFFWDEventMoodPrivacy",
    "ShipTestUs" : "PlayerCurrentShip",
    "ShipTestThem" : "PlayerCurrentShip",
    "LootCTsUs"      : null
  },
  {
    "strName" : "FFWDEventMoodWeird",
    "strTitle" : "Бормотать суеверно",
    "strDesc" : "[them] находит [us], который бормочет, жестикулирует и рисует суеверные символы и тексты на любых поверхностях.",
    "strActionGroup" : "Use",
    "strColor"      : "Dialogue",
    "aInverse"          : [
    ],
    "fDuration"         : 0.00,
    "strThemType"       : "Other",
    "nLogging"         : 1,
    "bHumanOnly"     : false,
    "bSocial" : true,
    "CTTestUs"     : "THasWeird0304Awake",
    "CTTestThem" : "TIsValidSocialTarget",
    "LootCondsUs"       : "CONDFFWDEventMoodWeird",
    "LootCondsThem"       : "CONDFFWDEventMoodWeird",
    "ShipTestUs" : "PlayerCurrentShip",
    "ShipTestThem" : "PlayerCurrentShip",
    "LootCTsUs"      : null
  },
  {
    "strName" : "FFWDEventMoodMerga",
    "strTitle" : "Смотреть в Пустоту",
    "strDesc" : "[us] делится с [them] чувствами, что нечто зловещее и могущественное охотится за ними.",
    "strActionGroup" : "Use",
    "strColor"      : "Dialogue",
    "aInverse"          : [
    ],
    "fDuration"         : 0.00,
    "strThemType"       : "Other",
    "nLogging"         : 1,
    "bHumanOnly"     : false,
    "bSocial" : true,
    "CTTestUs"     : "THasMerga040506Awake",
    "CTTestThem" : "TIsValidSocialTarget",
    "LootCondsUs"       : "CONDFFWDEventMoodWeird",
    "LootCondsThem"       : "CONDFFWDEventMoodWeird",
    "ShipTestUs" : "PlayerCurrentShip",
    "ShipTestThem" : "PlayerCurrentShip",
    "LootCTsUs"      : null
  },
  {
    "strName" : "FFWDEventSkillSong",
    "strTitle" : "Развлекать (песни)",
    "strDesc" : "[us] развлекал [them], поя catchy космические шанти и популярные гимны.",
    "strActionGroup" : "Use",
    "strColor"      : "Dialogue",
    "aInverse"          : [
    ],
    "fDuration"         : 0.00,
    "strThemType"       : "Other",
    "nLogging"         : 1,
    "bHumanOnly"     : false,
    "bSocial" : true,
    "CTTestUs"     : "TIsSkilledSongAwake",
    "CTTestThem" : "TIsValidSocialTarget",
    "LootCondsUs"       : "CONDFFWDEventSkillSongUs",
    "LootCondsThem"       : "CONDFFWDEventSkillSongThem",
    "ShipTestUs" : "PlayerCurrentShip",
    "ShipTestThem" : "PlayerCurrentShip",
    "LootCTsUs"      : null,
    "aSocialNew" : [
    ]
  },
  {
    "strName" : "FFWDEventSoloRememberFamily",
    "strTitle" : "Вспомнить семью",
    "strDesc" : "[us] вспоминает семью, думая о прошлых разговорах и моментах с [them].",
    "strActionGroup" : "Use",
    "strColor"      : "Dialogue",
    "aInverse"          : [
    ],
    "fDuration"         : 0.00,
    "strThemType"       : "Other",
    "nLogging"         : 1,
    "bHumanOnly"     : false,
    "CTTestUs"     : null,
    "PSpecTestThem" : "RELFamilyFind",
    "LootCondsUs"       : "CONDFFWDEventSoloMusingFamilyUs",
    "LootCondsThem"       : null,
    "ShipTestUs" : "PlayerCurrentShip",
    "LootCTsUs"      : null
  },
  {
    "strName" : "FFWDEventConverseFamily",
    "strTitle" : "Взаимодействовать с семьей",
    "strDesc" : "[us] ведет трудный, но важный разговор с [them]. Кровь гуще воды, иногда.",
    "strActionGroup" : "Use",
    "strColor"      : "Dialogue",
    "aInverse"          : [
    ],
    "fDuration"         : 0.00,
    "strThemType"       : "Other",
    "nLogging"         : 1,
    "bHumanOnly"     : false,
    "bSocial"  : true,
    "CTTestUs"     : "TIsValidSocialTarget",
    "PSpecTestThem" : "RELFamilyFindAwake",
    "ShipTestUs" : "PlayerCurrentShip",
    "ShipTestThem" : "PlayerCurrentShip",
    "LootCondsUs"       : "CONDFFWDEventSoloMusingFamilyUs",
    "LootCondsThem"       : "CONDFFWDEventSoloMusingFamilyUs",
    "LootCTsUs"      : null
  },
  {
    "strName" : "FFWDEventSoloRememberFriend",
    "strTitle" : "Вспомнить друга",
    "strDesc" : "[us] с теплотой вспоминает прошлые разговоры и моменты со своим другом [them].",
    "strActionGroup" : "Use",
    "strColor"      : "Dialogue",
    "aInverse"          : [
    ],
    "fDuration"         : 0.00,
    "strThemType"       : "Other",
    "nLogging"         : 1,
    "bHumanOnly"     : false,
    "CTTestUs"     : null,
    "PSpecTestThem" : "RELFriendFind",
    "LootCondsUs"       : "CONDFFWDEventSoloMusingFamilyUs",
    "LootCondsThem"       : null,
    "ShipTestUs" : "PlayerCurrentShip",
    "LootCTsUs"      : null
  },
  {
    "strName" : "FFWDEventConverseFriend",
    "strTitle" : "Общение с другом",
    "strDesc" : "[us] ведет трудный, но важный разговор с [them]. Дружба требует усилий!",
    "strActionGroup" : "Use",
    "strColor"      : "Dialogue",
    "aInverse"          : [
    ],
    "fDuration"         : 0.00,
    "strThemType"       : "Other",
    "nLogging"         : 1,
    "bHumanOnly"     : false,
    "bSocial"  : true,
    "CTTestUs"     : "TIsValidSocialTarget",
    "PSpecTestThem" : "RELFriendFindAwake",
    "ShipTestUs" : "PlayerCurrentShip",
    "ShipTestThem" : "PlayerCurrentShip",
    "LootCondsUs"       : "CONDFFWDEventSoloMusingFamilyUs",
    "LootCondsThem"       : "CONDFFWDEventSoloMusingFamilyUs",
    "LootCTsUs"      : null
  },
  {
    "strName" : "FFWDEventSoloRememberLover",
    "strTitle" : "Вспомнить любовника",
    "strDesc" : "[us] фантазирует о близости с [them].",
    "strActionGroup" : "Use",
    "strColor"      : "Dialogue",
    "aInverse"          : [
    ],
    "fDuration"         : 0.00,
    "strThemType"       : "Other",
    "nLogging"         : 1,
    "bHumanOnly"     : false,
    "CTTestUs"     : "TIsNotChaste",
    "PSpecTestThem" : "RELLover",
    "LootCondsUs"       : "CONDFFWDEventSoloMusingIntimateUs",
    "LootCondsThem"       : null,
    "ShipTestUs" : "PlayerCurrentShip",
    "LootCTsUs"      : null
  },
  {
    "strName" : "FFWDEventConverseLover",
    "strTitle" : "Общение с любовником",
    "strDesc" : "[us] нашел момент, чтобы разделить близость с [them].",
    "strActionGroup" : "Use",
    "strColor"      : "Dialogue",
    "aInverse"          : [
    ],
    "fDuration"         : 0.00,
    "strThemType"       : "Other",
    "nLogging"         : 1,
    "bHumanOnly"     : false,
    "bSocial"  : true,
    "CTTestUs"     : "TIsNotChasteAwake",
    "CTTestThem"     : "TIsNotChasteAwake",
    "PSpecTestThem" : "RELLoverFindAwake",
    "ShipTestUs" : "PlayerCurrentShip",
    "ShipTestThem" : "PlayerCurrentShip",
    "LootCondsUs"       : "CONDFFWDEventIntimateSharedUs",
    "LootCondsThem"       : "CONDFFWDEventIntimateSharedUs",
    "LootCTsUs"      : null
  },
  {
    "strName" : "FFWDEventSoloRememberEx",
    "strTitle" : "Мечты о потерянной любви",
    "strDesc" : "[us] фантазирует о потерянной любви с [them], прежде чем все охладилось.",
    "strActionGroup" : "Use",
    "strColor"      : "Dialogue",
    "aInverse"          : [
    ],
    "fDuration"         : 0.00,
    "strThemType"       : "Other",
    "nLogging"         : 1,
    "bHumanOnly"     : false,
    "CTTestUs"     : "TIsNotChaste",
    "PSpecTestThem" : "RELLoverEx",
    "LootCondsUs"       : "CONDFFWDEventSoloMusingIntimateNegUs",
    "LootCondsThem"       : null,
    "ShipTestUs" : "PlayerCurrentShip",
    "LootCTsUs"      : null
  },
  {
    "strName" : "FFWDEventSoloRememberIntimacy",
    "strTitle" : "Мечта о близости",
    "strDesc" : "[us] жаловался на одиночество и желание иметь любовника.",
    "strActionGroup" : "Use",
    "strColor"      : "Dialogue",
    "aInverse"          : [
    ],
    "fDuration"         : 0.00,
    "strThemType"       : "Other",
    "nLogging"         : 1,
    "bHumanOnly"     : false,
    "CTTestUs"     : "TIsValidSocialTargetLowIntimacy",
    "LootCondsUs"       : "CONDFFWDEventSoloMusingIntimateNegUs",
    "LootCondsThem"       : null,
    "LootCTsUs"      : null,
    "ShipTestUs" : "PlayerCurrentShip"
  },
  {
    "strName" : "FFWDEventConverseEx",
    "strTitle" : "Общение с бывшим",
    "strDesc" : "[us] имел неприятный конфликт с бывшим партнером [them].",
    "strActionGroup" : "Use",
    "strColor"      : "Dialogue",
    "aInverse"          : [
    ],
    "fDuration"         : 0.00,
    "strThemType"       : "Other",
    "nLogging"         : 1,
    "bHumanOnly"     : false,
    "bSocial"  : true,
    "CTTestUs"     : "TIsValidSocialTarget",
    "PSpecTestThem" : "RELLoverExFindAwake",
    "ShipTestUs" : "PlayerCurrentShip",
    "ShipTestThem" : "PlayerCurrentShip",
    "LootCondsUs"       : "CONDFFWDEventSoloMusingIntimateNegUs",
    "LootCondsThem"       : "CONDFFWDEventSoloMusingIntimateNegUs",
    "LootCTsUs"      : null
  },
  {
    "strName" : "FFWDEventSoloForgivingEnemy",
    "strTitle" : "Мечта о примирении",
    "strDesc" : "[us] размышлял о способах прощения и разрешения конфликтов с врагом [them].",
    "strActionGroup" : "Use",
    "strColor"      : "Dialogue",
    "aInverse"          : [
    ],
    "fDuration"         : 0.00,
    "strThemType"       : "Other",
    "nLogging"         : 1,
    "bHumanOnly"     : false,
    "bSocial"  : true,
    "CTTestUs"     : "TIsForgivingAwake",
    "PSpecTestThem" : "RELEnemyOrNemesis",
    "LootCondsUs"       : "CONDFFWDEventSoloMusingSelflessUs",
    "LootCondsThem"       : null,
    "LootCTsUs"      : null
  },
  {
    "strName" : "FFWDEventSoloVengeance",
    "strTitle" : "Мечта о мести",
    "strDesc" : "[us] мечтал о том, чтобы отдать своему врагу [them] то, что он заслуживает.",
    "strActionGroup" : "Use",
    "strColor"      : "Dialogue",
    "aInverse"          : [
    ],
    "fDuration"         : 0.00,
    "strThemType"       : "Other",
    "nLogging"         : 1,
    "bHumanOnly"     : false,
    "CTTestUs"     : "TIsVengefulAwake",
    "PSpecTestThem" : "RELEnemyOrNemesis",
    "LootCondsUs"       : "CONDFFWDEventSoloMusingPhilosophicalUs",
    "LootCondsThem"       : null,
    "LootCTsUs"      : null
  },
  {
    "strName" : "FFWDEventSoloCruelEnemy",
    "strTitle" : "Мечта о мести",
    "strDesc" : "[us] наслаждался мечтами о том, как их враг [them] терпит ужасные судьбы.",
    "strActionGroup" : "Use",
    "strColor"      : "Dialogue",
    "aInverse"          : [
    ],
    "fDuration"         : 0.00,
    "strThemType"       : "Other",
    "nLogging"         : 1,
    "bHumanOnly"     : false,
    "CTTestUs"     : "TIsCruelAwake",
    "PSpecTestThem" : "RELEnemyOrNemesis",
    "LootCondsUs"       : "CONDFFWDEventSoloMusingPhilosophicalUs",
    "LootCondsThem"       : null,
    "LootCTsUs"      : null
  },
  {
    "strName" : "FFWDEventSoloCruel",
    "strTitle" : "Мечта о мести",
    "strDesc" : "[us] представлял, как бы он мог выплеснуть свою агрессию на невинных космолетчиков или домашних животных.",
    "strActionGroup" : "Use",
    "strColor"      : "Dialogue",
    "aInverse"          : [
    ],
    "fDuration"         : 0.00,
    "strThemType"       : "Self",
    "nLogging"         : 1,
    "bHumanOnly"     : false,
    "CTTestUs"     : "TIsCruelAwake",
    "LootCondsUs"       : "CONDFFWDEventSoloMusingPhilosophicalNegUs",
    "LootCondsThem"       : null,
    "LootCTsUs"      : null
  },

  {
    "strName" : "FFWDEventSoloComplacent",
    "strTitle" : "Найти удовлетворение",
    "strDesc" : "[us] нашел удовлетворение в мелочах. Секрет счастья — желать того, что у тебя есть.",
    "strActionGroup" : "Use",
    "strColor"      : "Dialogue",
    "aInverse"          : [
    ],
    "fDuration"         : 0.00,
    "strThemType"       : "Self",
    "nLogging"         : 1,
    "bHumanOnly"     : false,
    "CTTestUs"     : "TIsComplacentAwake",
    "LootCondsUs"       : "CONDFFWDEventSoloMusingPhilosophicalUs",
    "LootCondsThem"       : null,
    "LootCTsUs"      : null
  },
  {
    "strName" : "FFWDEventSoloPatient",
    "strTitle" : "Терпеливое ожидание",
    "strDesc" : "[us] терпеливо ждал в комфортных размышлениях. Хорошие вещи приходят к тем, кто ждет.",
    "strActionGroup" : "Use",
    "strColor"      : "Dialogue",
    "aInverse"          : [
    ],
    "fDuration"         : 0.00,
    "strThemType"       : "Self",
    "nLogging"         : 1,
    "bHumanOnly"     : false,
    "CTTestUs"     : "TIsPatientAwake",
    "LootCondsUs"       : "CONDFFWDEventSoloMusingPhilosophicalUs",
    "LootCondsThem"       : null,
    "LootCTsUs"      : null
  },
  {
    "strName" : "FFWDEventSoloImpatient",
    "strTitle" : "Нетерпеливое мучение от времени",
    "strDesc" : "[us] мучился из-за потраченного времени. Время и прилив не ждут никого.",
    "strActionGroup" : "Use",
    "strColor"      : "Dialogue",
    "aInverse"          : [
    ],
    "fDuration"         : 0.00,
    "strThemType"       : "Self",
    "nLogging"         : 1,
    "bHumanOnly"     : false,
    "CTTestUs"     : "TIsImpatientAwake",
    "LootCondsUs"       : "CONDFFWDEventSoloMusingPhilosophicalUs",
    "LootCondsThem"       : null,
    "LootCTsUs"      : null
  },
  {
    "strName" : "FFWDEventApathetic",
    "strTitle" : "Плыть по течению",
    "strDesc" : "[us] наслаждался моментом, не беспокоясь ни о чем. Что будет, то будет.",
    "strActionGroup" : "Use",
    "strColor"      : "Dialogue",
    "aInverse"          : [
    ],
    "fDuration"         : 0.00,
    "strThemType"       : "Self",
    "nLogging"         : 1,
    "bHumanOnly"     : false,
    "CTTestUs"     : "TIsApatheticAwake",
    "LootCondsUs"       : "CONDFFWDEventSoloMusingPhilosophicalUs",
    "LootCondsThem"       : null,
    "LootCTsUs"      : null
  },
  {
    "strName" : "FFWDEventSkillSpaceship",
    "strTitle" : "Дизайн инженерии космического корабля",
    "strDesc" : "[us] мечтал о переработке дизайна корабля.",
    "strActionGroup" : "Use",
    "strColor"      : "Dialogue",
    "aInverse"          : [
    ],
    "fDuration"         : 0.00,
    "strThemType"       : "Self",
    "nLogging"         : 1,
    "bHumanOnly"     : false,
    "CTTestUs"     : "TIsSkilledEngSpaceship",
    "LootCondsUs"       : "CONDFFWDEventSoloMusingUs",
    "LootCondsThem"       : null,
    "LootCTsUs"      : null
  },
  {
    "strName" : "FFWDEventSkillSoftware",
    "strTitle" : "Обновление программного обеспечения",
    "strDesc" : "Очистил управление и повторно проверил программное обеспечение [them].",
    "strActionGroup" : "Use",
    "strColor"      : "Dialogue",
    "aInverse"          : [
    ],
    "fDuration"         : 0.00,
    "strThemType"       : "Other",
    "nLogging"         : 1,
    "bHumanOnly"     : false,
    "CTTestUs"     : "TIsSkilledSoftwareAwake",
    "CTTestThem"     : "TIsNavStationInstalled",
    "ShipTestThem" : "PlayerCurrentShip",
    "LootCondsUs"       : "CONDFFWDEventSoloMusingUs",
    "LootCondsThem"       : "CONDFFWDEventSkillEngSoftwareNavThem",
    "LootCTsUs"      : null
  },
  {
    "strName" : "FFWDEventSkillElectronicBatteries",
    "strTitle" : "Обновление батареи электронной инженерии",
    "strDesc" : "[us] очистил соединения и коррозию на [them].",
    "strActionGroup" : "Use",
    "strColor"      : "Dialogue",
    "aInverse"          : [
    ],
    "fDuration"         : 0.00,
    "strThemType"       : "Other",
    "nLogging"         : 1,
    "bHumanOnly"     : false,
    "CTTestUs"     : "TIsSkilledPOWRAwake",
    "CTTestThem"     : "TIsShipBatteryInstalled",
    "ShipTestThem" : "PlayerCurrentShip",
    "LootCondsUs"       : "CONDFFWDEventSoloMusingUs",
    "LootCondsThem"       : "CONDFFWDEventMinorRepairThem",
    "LootCTsUs"      : null
  },
  {
    "strName" : "FFWDEventSkillElectronic",
    "strTitle" : "Обновление электронной инженерии",
    "strDesc" : "[us] потратил время на перезаправку [them].",
    "strActionGroup" : "Use",
    "strColor"      : "Dialogue",
    "aInverse"          : [
    ],
    "fDuration"         : 0.00,
    "strThemType"       : "Other",
    "nLogging"         : 1,
    "bHumanOnly"     : false,
    "CTTestUs"     : "TIsSkilledPOWRAwake",
    "CTTestThem"     : "TIsElectronicInstalled",
    "ShipTestThem" : "PlayerCurrentShip",
    "LootCondsUs"       : "CONDFFWDEventSoloMusingUs",
    "LootCondsThem"       : "CONDFFWDEventMinorRepairThem",
    "LootCTsUs"      : null
  },
  
  {
    "strName" : "FFWDEventAdmiringShipParts",
    "strTitle" : "Уборка на корабле",
    "strDesc" : "[us] восхищался [them]. Разве это не прекрасно?",
    "strActionGroup" : "Use",
    "strColor"      : "Dialogue",
    "aInverse"          : [
    ],
    "fDuration"         : 0.00,
    "strThemType"       : "Other",
    "nLogging"         : 1,
    "bHumanOnly"     : false,
    "CTTestUs"     : "TIsValidSocialTarget",
    "CTTestThem"     : "TIsDecorInstalled",
    "ShipTestThem" : "PlayerCurrentShip",
    "LootCondsUs"       : "CONDFFWDEventSoloMusingUs",
    "LootCTsUs"      : null
  },
  {
    "strName" : "FFWDEventFinickyCleaningShipParts",
    "strTitle" : "Уборка на корабле",
    "strDesc" : "[us] снова очистил [them], просто чтобы быть уверенным.",
    "strActionGroup" : "Use",
    "strColor"      : "Dialogue",
    "aInverse"          : [
    ],
    "fDuration"         : 0.00,
    "strThemType"       : "Other",
    "nLogging"         : 1,
    "bHumanOnly"     : false,
    "CTTestUs"     : "TIsFinickyOrTidyAwake",
    "CTTestThem"     : "TIsShipPartCleaningTarget",
    "ShipTestThem" : "PlayerCurrentShip",
    "LootCondsUs"       : "CONDFFWDEventSoloMusingUs",
    "LootCondsThem"       : "CONDFFWDEventMinorRepairThem",
    "LootCTsUs"      : null
  },
  {
    "strName" : "FFWDEventTendingShipParts",
    "strTitle" : "",
    "strDesc" : "[us] занимался [them].",
    "strActionGroup" : "Use",
    "strColor"      : "Dialogue",
    "aInverse"          : [
    ],
    "fDuration"         : 0.00,
    "strThemType"       : "Other",
    "nLogging"         : 1,
    "bHumanOnly"     : false,
    "CTTestUs"     : "TIsSkilledEngineerAwake",
    "CTTestThem"     : "TIsShipPartTendingTarget",
    "ShipTestThem" : "PlayerCurrentShip",
    "LootCondsUs"       : "CONDFFWDEventSoloMusingUs",
    "LootCondsThem"       : "CONDFFWDEventMinorRepairThem",
    "LootCTsUs"      : null
  },  
  {
    "strName" : "FFWDEventMakeMessShipParts",
    "strTitle" : "Уборка на корабле",
    "strDesc" : "[us] снова оставил [them] в беспорядке.",
    "strActionGroup" : "Use",
    "strColor"      : "Dialogue",
    "aInverse"          : [
    ],
    "fDuration"         : 0.00,
    "strThemType"       : "Other",
    "nLogging"         : 1,
    "bHumanOnly"     : false,
    "CTTestUs"     : "TIsSlovenlyAwake",
    "CTTestThem"     : "TIsShipPartCleaningTarget",
    "ShipTestThem" : "PlayerCurrentShip",
    "LootCondsUs"       : "CONDFFWDEventSoloMusingUs",
    "LootCondsThem"       : null,
    "LootCTsUs"      : null
  },
  {
    "strName" : "FFWDEventTendingAppearance",
    "strTitle" : "Забота о внешности",
    "strDesc" : "[us] занимается рутиной ухода за собой, чтобы выглядеть красиво.",
    "strActionGroup" : "Use",
    "strColor"      : "Dialogue",
    "aInverse"          : [
    ],
    "fDuration"         : 0.00,
    "strThemType"       : "Self",
    "nLogging"         : 1,
    "bHumanOnly"     : false,
    "CTTestUs"     : "TIsBeautifulAwake",
    "LootCondsUs"       : "CONDFFWDEventSoloMusingGroomingUs",
    "LootCTsUs"      : null
  },
  {
    "strName" : "FFWDEventTendingAppearanceSink",
    "strTitle" : "Забота о внешности у раковины",
    "strDesc" : "[us] проводит много времени у [them], приводя себя в порядок и улучшая свой внешний вид.",
    "strActionGroup" : "Use",
    "strColor"      : "Dialogue",
    "aInverse"          : [
    ],
    "fDuration"         : 0.00,
    "strThemType"       : "Other",
    "nLogging"         : 1,
    "bHumanOnly"     : false,
    "CTTestUs"     : "TIsBeautifulAwake",
    "CTTestThem"     : "TIsSinkInstalled",
    "ShipTestThem" : "PlayerCurrentShip",
    "LootCondsUs"       : "CONDFFWDEventSoloMusingGroomingUs",
    "LootCTsUs"      : null
  },
  {
    "strName" : "FFWDEventTendingAppearanceUgly",
    "strTitle" : "Забота о внешности при отвращении",
    "strDesc" : "[us] погружается в самоотверженное отвращение к [them], критикуя свой внешний вид.",
    "strActionGroup" : "Use",
    "strColor"      : "Dialogue",
    "aInverse"          : [
    ],
    "fDuration"         : 0.00,
    "strThemType"       : "Other",
    "nLogging"         : 1,
    "bHumanOnly"     : false,
    "CTTestUs"     : "TIsUglyAwake",
    "CTTestThem"     : "TIsSinkInstalled",
    "ShipTestThem" : "PlayerCurrentShip",
    "LootCondsUs"       : "CONDFFWDEventSoloMusingGroomingNegUs",
    "LootCTsUs"      : null
  },
  {
    "strName" : "FFWDEventTemperate",
    "strTitle" : "Умеренность",
    "strDesc" : "[us] сопротивляется желанию насладиться маленьким удовольствием.",
    "strActionGroup" : "Use",
    "strColor"      : "Dialogue",
    "aInverse"          : [
    ],
    "fDuration"         : 0.00,
    "strThemType"       : "Other",
    "nLogging"         : 1,
    "bHumanOnly"     : false,
    "CTTestUs"     : "TIsTemperateAwake",
    "LootCondsUs"       : "CONDFFWDEventSoloMusingUs",
    "LootCTsUs"      : null
  },
  {
    "strName" : "FFWDEventGluttonIndulgenceCarried",
    "strTitle" : "Проявление жадности",
    "strDesc" : "[us] не сопротивляется желанию насладиться маленьким удовольствием и погружается в [them] себе одному.",
    "strActionGroup" : "Use",
    "strColor"      : "Dialogue",
    "aInverse"          : [
    ],
    "fDuration"         : 0.00,
    "strThemType"       : "Other",
    "nLogging"         : 1,
    "bHumanOnly"     : false,
    "CTTestUs"     : "TIsGluttonAwake",
    "LootCondsUs"       : "CONDFFWDEventSoloGluttonIndulgenceUs",
    "CTTestThem"     : "TIsGluttonTarget",
    "ShipTestThem" : "PlayerCurrentShip",
    "LootCTsUs"      : null,
    "aLootItms" : [ "RemoveUs,CTGluttonIndulgence,false,true,false" ]
  }
]